LICENSE
drf_integrations/__init__.py
drf_integrations/admin.py
drf_integrations/apps.py
drf_integrations/auth_backends.py
drf_integrations/exceptions.py
drf_integrations/fields.py
drf_integrations/forms.py
drf_integrations/integrations/__init__.py
drf_integrations/integrations/base.py
drf_integrations/integrations/managers.py
drf_integrations/integrations/models.py
drf_integrations/integrations/registry.py
drf_integrations/management/__init__.py
drf_integrations/management/commands/__init__.py
drf_integrations/management/commands/syncregistry.py
drf_integrations/managers.py
drf_integrations/migrations/0001_initial.py
drf_integrations/migrations/0002_auto_20200623_1421.py
drf_integrations/migrations/0003_auto_20210118_1317.py
drf_integrations/migrations/0004_auto_20220503_1428.py
drf_integrations/migrations/0005_alter_applicationinstallation_id.py
drf_integrations/migrations/__init__.py
drf_integrations/models.py
drf_integrations/types.py
drf_integrations/urls.py
drf_integrations/utils.py
drf_integrations_framework-0.8.7.dist-info/LICENSE
drf_integrations_framework-0.8.7.dist-info/METADATA
drf_integrations_framework-0.8.7.dist-info/WHEEL
drf_integrations_framework-0.8.7.dist-info/RECORD
