Metadata-Version: 2.1
Name: drf-integrations-framework
Version: 0.8.7
Summary: Django REST Framework plugin that simplifies the management of third party integrations
Home-page: https://github.com/yoyowallet/drf-integrations-framework
License: MIT
Keywords: drf
Author: Yoyo
Author-email: dev@yoyowallet.com
Requires-Python: >=3.7,<3.12
Classifier: Development Status :: 3 - Alpha
Classifier: Framework :: Django
Classifier: Intended Audience :: Developers
Classifier: License :: OSI Approved :: MIT License
Classifier: Operating System :: OS Independent
Classifier: Programming Language :: Python :: 3
Classifier: Programming Language :: Python :: 3.7
Classifier: Programming Language :: Python :: 3.8
Classifier: Programming Language :: Python :: 3.9
Classifier: Programming Language :: Python :: 3.10
Classifier: Programming Language :: Python :: 3.11
Classifier: Topic :: Software Development :: Libraries
Requires-Dist: Pillow (>=7.0.0,<10.0.0)
Requires-Dist: django-environ (>=0.9.0)
Requires-Dist: django-oauth-toolkit (>=1.3,<1.5)
Requires-Dist: djangorestframework (>=3.11.0,<4)
Project-URL: Repository, https://github.com/yoyowallet/drf-integrations-framework
